assay_analyze.py
assay_blast.py
assay_test.py
assay_blast-2.0.dist-info/licenses/LICENSE
assay_blast-2.0.dist-info/METADATA
assay_blast-2.0.dist-info/WHEEL
assay_blast-2.0.dist-info/entry_points.txt
assay_blast-2.0.dist-info/top_level.txt
assay_blast-2.0.dist-info/RECORD
